[
    {"url": "./co2/data.json", "id": "co2_data"},
    {"url": "./aerosol/data.json", "id": "aerosol_data"},
    {"url": "./solar/data.json", "id": "solar_data"},
    {"url": "./volcanic/data.json", "id": "volcanic_data"},
    "./solar/parser.coffee",
    "./co2/parser.coffee",
    "./aerosol/parser.coffee",
    "./volcanic/parser.coffee",
    "http://puzlet.org/utility/array.coffee",
    "http://puzlet.org/utility/math.coffee",
    "forcing.coffee",
    "main.coffee",
    "main.css",
    "main.html"
]
